imagedownloader/__init__.py
imagedownloader/__main__.py
imagedownloader/imagedownloader.py
imagedownloader-1.0.3.dist-info/LICENSE
imagedownloader-1.0.3.dist-info/METADATA
imagedownloader-1.0.3.dist-info/WHEEL
imagedownloader-1.0.3.dist-info/top_level.txt
imagedownloader-1.0.3.dist-info/RECORD
