Metadata-Version: 2.1
Name: imagedownloader
Version: 1.0.3
Summary: Python Package to Download Images
Home-page: https://github.com/mm-mazhar/imagedownloader.git
Download-URL: https://github.com/mm-mazhar/imagedownloader.git
Author: Mazhar
Author-email: mazqoty.01@gmail.com
Maintainer: Mazhar
Maintainer-email: mazqoty.01@gmail.com
License: BSD
Project-URL: Bug Tracker, https://github.com/mm-mazhar/imagedownloader/issues
Keywords: Download Images,Get Images,Python,ImageDownloader,Python Package,Downloads
Classifier: Intended Audience :: Developers
Classifier: License :: OSI Approved :: BSD License
Classifier: Operating System :: POSIX :: Linux
Classifier: Programming Language :: Python
Requires-Python: >=3.7
License-File: LICENSE
Requires-Dist: requests (==2.27.1)
Requires-Dist: setuptools (==65.6.3)
